sqredirect/__init__.py
sqredirect/redirect.c
sqredirect/redirect.py
sqredirect/utils.h
sqredirect-1.2.2.dist-info/entry_points.txt
sqredirect-1.2.2.dist-info/LICENSE
sqredirect-1.2.2.dist-info/WHEEL
sqredirect-1.2.2.dist-info/METADATA
sqredirect-1.2.2.dist-info/RECORD
