Metadata-Version: 2.1
Name: sqredirect
Version: 1.2.2
Summary: 
Author: spumer
Author-email: spumer-tm@yandex.ru
Requires-Python: >=3.6,<4.0
Classifier: Programming Language :: Python :: 3
Classifier: Programming Language :: Python :: 3.10
Classifier: Programming Language :: Python :: 3.6
Classifier: Programming Language :: Python :: 3.7
Classifier: Programming Language :: Python :: 3.8
Classifier: Programming Language :: Python :: 3.9
Requires-Dist: py2-ipaddress (>=3.4.2,<4.0.0); python_version >= "2.7" and python_version < "3.0"
Requires-Dist: pyroute2 (>=0.4)
